test_arbitrary_pip_package_testn0lv/__init__.py
test_arbitrary_pip_package_junkn0lv-0.2.0.dist-info/METADATA
test_arbitrary_pip_package_junkn0lv-0.2.0.dist-info/WHEEL
test_arbitrary_pip_package_junkn0lv-0.2.0.dist-info/top_level.txt
test_arbitrary_pip_package_junkn0lv-0.2.0.dist-info/RECORD
